__init__.py
optioner.py
optioner-1.5.2.dist-info/LICENSE
optioner-1.5.2.dist-info/METADATA
optioner-1.5.2.dist-info/WHEEL
optioner-1.5.2.dist-info/top_level.txt
optioner-1.5.2.dist-info/RECORD
