Metadata-Version: 2.1
Name: optioner
Version: 1.5.2
Summary: Argument Parser
Author-email: Soumyo Deep Gupta <deep.main.ac@gmail.com>
Maintainer-email: Soumyo Deep Gupta <deep.main.ac@gmail.com>
License: MIT License
Project-URL: GitHub, https://github.com/d33pster/optioner
Project-URL: Issues, https://github.com/d33pster/optioner/issues
Project-URL: Documentation, https://d33pster.github.io/optioner/
Keywords: d33pster,optioner,argument-parser,argument,parser,argparse
Classifier: Development Status :: 5 - Production/Stable
Classifier: Intended Audience :: Developers
Classifier: Topic :: Software Development :: Build Tools
Classifier: Programming Language :: Python :: 3.9
Classifier: Programming Language :: Python :: 3.10
Classifier: Programming Language :: Python :: 3.11
Classifier: Programming Language :: Python :: 3.12
Classifier: License :: OSI Approved :: MIT License
Classifier: Operating System :: OS Independent
Requires-Python: >=3.9
License-File: LICENSE
